{
  "vmware.vmware.appliance_info": {
    "short_description": "Gather appliance information",
    "description": "This module gather VCenter appliance information.",
    "options": {
      "properties": {
        "description": "Specify the properties to retrieve. If not specified, all properties are retrieved.",
        "type": "list",
        "required": false,
        "choices": [
          "summary",
          "access",
          "networking",
          "firewall",
          "time",
          "services",
          "update",
          "syslog",
          "all"
        ],
        "default": "all",
        "aliases": null
      }
    },
    "deprecated": null
  },
  "vmware.vmware.cluster": {
    "short_description": "Manage VMware vSphere clusters",
    "description": "Adds or removes VMware vSphere clusters. To manage DRS, HA and VSAN related configurations, use the modules cluster_drs, community.vmware.vmware_cluster_ha and community.vmware.vmware_cluster_vsan.",
    "options": {
      "cluster": {
        "description": "The name of the cluster to be managed.",
        "type": "str",
        "required": true,
        "choices": null,
        "default": null,
        "aliases": [
          "cluster_name",
          "name"
        ]
      },
      "datacenter": {
        "description": "The name of the datacenter.",
        "type": "str",
        "required": true,
        "choices": null,
        "default": null,
        "aliases": [
          "datacenter_name"
        ]
      },
      "state": {
        "description": "Create V(present) or remove V(absent) a VMware vSphere cluster.",
        "type": "str",
        "required": false,
        "choices": [
          "absent",
          "present"
        ],
        "default": "present",
        "aliases": null
      }
    },
    "deprecated": null
  },
  "vmware.vmware.cluster_dpm": {
    "short_description": "Manage Distributed Power Management (DPM) on VMware vSphere clusters",
    "description": "Manages DPM on VMware vSphere clusters.",
    "options": {
      "cluster": {
        "description": "The name of the cluster to be managed.",
        "type": "str",
        "required": true,
        "choices": null,
        "default": null,
        "aliases": [
          "cluster_name"
        ]
      },
      "datacenter": {
        "description": "The name of the datacenter.",
        "type": "str",
        "required": true,
        "choices": null,
        "default": null,
        "aliases": [
          "datacenter_name"
        ]
      },
      "enable": {
        "description": "Whether to enable DPM.",
        "type": "bool",
        "required": false,
        "choices": null,
        "default": true,
        "aliases": null
      },
      "automation_level": {
        "description": "Determines whether the host power state and migration recommendations generated by vSphere DPM are run automatically or manually. If set to V(manual), then vCenter generates host power operation and related virtual machine migration recommendations are made, but they are not automatically run. If set to V(automatic), then vCenter host power operations are automatically run if related virtual machine migrations can all be run automatically.",
        "type": "str",
        "required": false,
        "choices": [
          "automatic",
          "manual"
        ],
        "default": "automatic",
        "aliases": null
      },
      "recommendation_priority_threshold": {
        "description": "Threshold for generated host power recommendations ranging from V(1) (most conservative) to V(5) (most aggressive). The power state (host power on or off) recommendations generated by the vSphere DPM feature are assigned priorities that range from priority V(1) recommendations to priority V(5) recommendations. A priority V(1) recommendation is mandatory, while a priority V(5) recommendation brings only slight improvement",
        "type": "int",
        "required": false,
        "choices": [
          1,
          2,
          3,
          4,
          5
        ],
        "default": 3,
        "aliases": null
      }
    },
    "deprecated": null
  },
  "vmware.vmware.cluster_drs": {
    "short_description": "Manage Distributed Resource Scheduler (DRS) on VMware vSphere clusters",
    "description": "Manages DRS on VMware vSphere clusters.",
    "options": {
      "cluster": {
        "description": "The name of the cluster to be managed.",
        "type": "str",
        "required": true,
        "choices": null,
        "default": null,
        "aliases": [
          "cluster_name"
        ]
      },
      "datacenter": {
        "description": "The name of the datacenter.",
        "type": "str",
        "required": true,
        "choices": null,
        "default": null,
        "aliases": [
          "datacenter_name"
        ]
      },
      "enable": {
        "description": "Whether to enable DRS.",
        "type": "bool",
        "required": false,
        "choices": null,
        "default": true,
        "aliases": null
      },
      "drs_enable_vm_behavior_overrides": {
        "description": "Whether DRS Behavior overrides for individual virtual machines are enabled. If set to V(true), overrides O(drs_default_vm_behavior).",
        "type": "bool",
        "required": false,
        "choices": null,
        "default": true,
        "aliases": null
      },
      "drs_default_vm_behavior": {
        "description": "Specifies the cluster-wide default DRS behavior for virtual machines. If set to V(partiallyAutomated), vCenter generates recommendations for virtual machine migration and for the placement with a host, then automatically implements placement recommendations at power on. If set to V(manual), then vCenter generates recommendations for virtual machine migration and for the placement with a host, but does not implement the recommendations automatically. If set to V(fullyAutomated), then vCenter automates both the migration of virtual machines and their placement with a host at power on.",
        "type": "str",
        "required": false,
        "choices": [
          "fullyAutomated",
          "manual",
          "partiallyAutomated"
        ],
        "default": "fullyAutomated",
        "aliases": null
      },
      "drs_vmotion_rate": {
        "description": "Threshold for generated ClusterRecommendations ranging from V(1) (lowest) to V(5) (highest).",
        "type": "int",
        "required": false,
        "choices": [
          1,
          2,
          3,
          4,
          5
        ],
        "default": 3,
        "aliases": null
      },
      "advanced_settings": {
        "description": "A dictionary of advanced DRS settings.",
        "type": "dict",
        "required": false,
        "choices": null,
        "default": {},
        "aliases": null
      },
      "predictive_drs": {
        "description": "In addition to real-time metrics, DRS will respond to forecasted metrics provided by vRealize Operations Manager. You must also configure Predictive DRS in a version of vRealize Operations that supports this feature.",
        "type": "bool",
        "required": false,
        "choices": null,
        "default": false,
        "aliases": null
      }
    },
    "deprecated": null
  },
  "vmware.vmware.cluster_drs_recommendations": {
    "short_description": "Apply Distributed Resource Scheduler (DRS) recommendations on VMware vSphere clusters",
    "description": "Applies DRS recommendations on VMware vSphere clusters. DRS recommendations are made based on a variety of factors such as resource usage, host health, and some advanced settings like TryBalanceVmsPerHost. The cluster may not recommend moving a VM if the cost of moving the VM is greater than the benefit that would come after the move. Recommendations may only be made if the VM can be vMotioned onto another host. Even if a host is clearly overloaded, if the VMs cannot move to another host then no recommendations will appear. If you try manually vMotioning a VM through the GUI, vCenter will validate the vMotion options at each step. This can be useful when determining why a VM is not able to move to another host and why no recommendations are being made.",
    "options": {
      "cluster": {
        "description": "The name of the cluster to be managed.",
        "type": "str",
        "required": true,
        "choices": null,
        "default": null,
        "aliases": [
          "cluster_name"
        ]
      },
      "datacenter": {
        "description": "The name of the datacenter.",
        "type": "str",
        "required": true,
        "choices": null,
        "default": null,
        "aliases": [
          "datacenter_name"
        ]
      }
    },
    "deprecated": null
  },
  "vmware.vmware.cluster_ha": {
    "short_description": "Manage High Availability services (HA) on VMware vSphere clusters",
    "description": "Manages HA on VMware vSphere clusters.",
    "options": {
      "cluster": {
        "description": "The name of the cluster to be managed.",
        "type": "str",
        "required": true,
        "choices": null,
        "default": null,
        "aliases": [
          "cluster_name"
        ]
      },
      "datacenter": {
        "description": "The name of the datacenter.",
        "type": "str",
        "required": true,
        "choices": null,
        "default": null,
        "aliases": [
          "datacenter_name"
        ]
      },
      "enable": {
        "description": "Whether to enable HA.",
        "type": "bool",
        "required": false,
        "choices": null,
        "default": true,
        "aliases": null
      },
      "host_failure_response": {
        "description": "Configures how VM workflows should be managed if an ESXi host is in a failure state.",
        "type": "dict",
        "required": false,
        "choices": null,
        "default": null,
        "aliases": null
      }
    },
    "deprecated": null
  },
  "vmware.vmware.cluster_info": {
    "short_description": "Gathers information about one or more clusters",
    "description": "Gathers information about one or more clusters. You can search for clusters based on the cluster name, datacenter name, or a combination of the two.",
    "options": {
      "cluster": {
        "description": "The name of the cluster on which to gather info. At least one of O(datacenter) or O(cluster) is required.",
        "type": "str",
        "required": false,
        "choices": null,
        "default": null,
        "aliases": [
          "cluster_name",
          "name"
        ]
      },
      "datacenter": {
        "description": "The name of the datacenter. At least one of O(datacenter) or O(cluster) is required.",
        "type": "str",
        "required": false,
        "choices": null,
        "default": null,
        "aliases": [
          "datacenter_name"
        ]
      },
      "gather_tags": {
        "description": "If true, gather any tags attached to the cluster(s) This has no affect if the O(schema) is set to V(vsphere). In that case, add",
        "type": "str",
        "required": false,
        "choices": null,
        "default": null,
        "aliases": null
      }
    },
    "deprecated": null
  },
  "vmware.vmware.cluster_vcls": {
    "short_description": "Manage the vCLS (vSphere Cluster Services) VM disk placement for this cluster.",
    "description": "Overrides the default vCLS VM disk placement for this cluster. Datastores may not be configured for vCLS if they are blocked by solutions where vCLS cannot be configured such as SRM or vSAN maintenance mode.",
    "options": {
      "cluster": {
        "description": "The name of the cluster to be managed.",
        "type": "str",
        "required": true,
        "choices": null,
        "default": null,
        "aliases": [
          "cluster_name"
        ]
      },
      "datacenter": {
        "description": "The name of the datacenter where the cluster and datastores can be found. If the cluster_name is unique for your environment, the datacenter is optional.",
        "type": "str",
        "required": false,
        "choices": null,
        "default": null,
        "aliases": [
          "datacenter_name"
        ]
      },
      "allowed_datastores": {
        "description": "Exclusive list of the allowed datastores. If there is an existing list configured in vCenter, it will be overridden by this value.",
        "type": "list",
        "required": false,
        "choices": null,
        "default": null,
        "aliases": null
      },
      "datastores_to_add": {
        "description": "List of datastores to add to the vCLS config The module will make sure these datastores are present in the config, and not change other datastores that are present.",
        "type": "list",
        "required": false,
        "choices": null,
        "default": [],
        "aliases": null
      },
      "datastores_to_remove": {
        "description": "List of datastores to remove from the vCLS config The module will make sure these datastores are absent from the config, and not change other datastores that are present.",
        "type": "list",
        "required": false,
        "choices": null,
        "default": [],
        "aliases": null
      }
    },
    "deprecated": null
  },
  "vmware.vmware.content_library_item_info": {
    "short_description": "Gather info about content library items.",
    "description": "Gather info about content library items, using optional search parameters to refine output. Content Library feature is introduced in vSphere 6.0 version. This module does not work with vSphere version older than 67U2. If neither O(library_item_id) nor O(library_item_name) are provided, all items in the relevant libraries will be returned.",
    "options": {
      "library_id": {
        "description": "The ID of the library to search within. Mutually exclusive with O(library_name) If neither O(library_id) nor O(library_name) are provided, all libraries will be considered relevant when searching.",
        "type": "str",
        "required": false,
        "choices": null,
        "default": null,
        "aliases": null
      },
      "library_name": {
        "description": "The name of the library to search within. Mutually exclusive with O(library_id) If neither O(library_id) nor O(library_name) are provided, all libraries will be considered relevant when searching.",
        "type": "str",
        "required": false,
        "choices": null,
        "default": null,
        "aliases": null
      },
      "library_item_id": {
        "description": "The ID of the library item for which to search. Mutually exclusive with O(library_item_name). Also mutually exclusive with O(library_id), and O(library_name) since item IDs are unique within a vCenter. If O(library_id) or O(library_name) are defined, only items in that library will be included in the results. If neither O(library_item_id) nor O(library_item_name) are provided, all items in the relevant libraries will be returned.",
        "type": "str",
        "required": false,
        "choices": null,
        "default": null,
        "aliases": null
      },
      "library_item_name": {
        "description": "The ID of the library item for which to search. Mutually exclusive with O(library_item_id). If O(library_id) or O(library_name) are defined, only items in that library will be included in the results. If neither O(library_item_id) nor O(library_item_name) are provided, all items in the relevant libraries will be returned.",
        "type": "str",
        "required": false,
        "choices": null,
        "default": null,
        "aliases": null
      }
    },
    "deprecated": null
  },
  "vmware.vmware.content_template": {
    "short_description": "Manage template in content library from virtual machine.",
    "description": "Module to manage template in content library from virtual machine. Content Library feature is introduced in vSphere 6.0 version. This module does not work with vSphere version older than 67U2.",
    "options": {
      "vm_name": {
        "description": "The name of the VM to be used to create template. Virtual machine names in vCenter are not necessarily unique, which may be problematic, see O(vm_name_match). This is required if O(vm_moid) or O(vm_uuid) is not supplied. A VM identifier is required when O(state) is present.",
        "type": "str",
        "required": false,
        "choices": null,
        "default": null,
        "aliases": null
      },
      "vm_name_match": {
        "description": "If multiple virtual machines matching the name, use the first or last found.",
        "type": "str",
        "required": false,
        "choices": [
          "first",
          "last"
        ],
        "default": "first",
        "aliases": null
      },
      "vm_uuid": {
        "description": "UUID of the instance to manage if known, this is VMware",
        "type": "str",
        "required": false,
        "choices": null,
        "default": null,
        "aliases": null
      }
    },
    "deprecated": null
  },
  "vmware.vmware.deploy_content_library_ovf": {
    "short_description": "Deploy a virtual machine from an OVF in a content library.",
    "description": "Create a VM based on an OVF in a content library. The module basis idempotentency on if the deployed VM exists or not, not the storage or deployment spec applied at deployment time.",
    "options": {
      "library_item_name": {
        "description": "The name of content library template to use when deploying the VM. This option is mutually exclusive with O(library_item_id). One of either O(library_item_name) or O(library_item_id) is required.",
        "type": "str",
        "required": false,
        "choices": null,
        "default": null,
        "aliases": [
          "template_name"
        ]
      },
      "library_item_id": {
        "description": "The ID of content library template to use when deploying the VM. This option is mutually exclusive with O(library_item_name). One of either O(library_item_name) or O(library_item_id) is required.",
        "type": "str",
        "required": false,
        "choices": null,
        "default": null,
        "aliases": [
          "template_id"
        ]
      },
      "library_name": {
        "description": "The name of the content library where the template exists. This is an optional parameter, but may be required if you use O(template_name) and have multiple templates in different libraries with the same name. This option is mutually exclusive with O(library_id).",
        "type": "str",
        "required": false,
        "choices": null,
        "default": null,
        "aliases": null
      },
      "library_id": {
        "description": "The ID of the content library where the template exists. This is an optional parameter, but may be required if you use O(template_name) and have multiple templates in different libraries with the same name. This option is mutually exclusive with O(library_name).",
        "type": "str",
        "required": false,
        "choices": null,
        "default": null,
        "aliases": null
      },
      "storage_provisioning": {
        "description": "Default storage provisioning type to use for all sections of type vmw:StorageSection in the OVF descriptor.",
        "type": "str",
        "required": false,
        "choices": null,
        "default": null,
        "aliases": null
      }
    },
    "deprecated": null
  },
  "vmware.vmware.deploy_content_library_template": {
    "short_description": "Deploy a virtual machine from a template in a content library.",
    "description": "Create a VM based on a template in a content library. The module basis idempotentency on if the deployed VM exists or not, not the storage or power settings applied at deployment time.",
    "options": {
      "library_item_name": {
        "description": "The name of content library template to use when deploying the VM. This option is mutually exclusive with O(library_item_id). One of either O(library_item_name) or O(library_item_id) is required.",
        "type": "str",
        "required": false,
        "choices": null,
        "default": null,
        "aliases": [
          "template_name"
        ]
      },
      "library_item_id": {
        "description": "The ID of content library template to use when deploying the VM. This option is mutually exclusive with O(library_item_name). One of either O(library_item_name) or O(library_item_id) is required.",
        "type": "str",
        "required": false,
        "choices": null,
        "default": null,
        "aliases": [
          "template_id"
        ]
      },
      "library_name": {
        "description": "The name of the content library where the template exists. This is an optional parameter, but may be required if you use O(template_name) and have multiple templates in different libraries with the same name. This option is mutually exclusive with O(library_id).",
        "type": "str",
        "required": false,
        "choices": null,
        "default": null,
        "aliases": null
      },
      "library_id": {
        "description": "The ID of the content library where the template exists. This is an optional parameter, but may be required if you use O(template_name) and have multiple templates in different libraries with the same name. This option is mutually exclusive with O(library_name).",
        "type": "str",
        "required": false,
        "choices": null,
        "default": null,
        "aliases": null
      },
      "esxi_host": {
        "description": "The name of the ESXi host onto which the virtual machine should be deployed. If O(esxi_host) and O(resource_pool) are both specified, O(resource_pool) must belong to O(esxi_host). If O(esxi_host) and O(cluster) are both specified, O(esxi_host) must be a member of O(cluster). Changing this option will not result in the VM being redeployed (it does not affect idempotency).",
        "type": "str",
        "required": false,
        "choices": null,
        "default": null,
        "aliases": [
          "host"
        ]
      },
      "power_on_after_deploy": {
        "description": "Whether or not the VM should be powered on once it has been deployed. This is only applied when the VM is deployed. If the VM already exists, the power state is not modified. Changing this option will not result in the VM being redeployed (it does not affect idempotency).",
        "type": "bool",
        "required": false,
        "choices": null,
        "default": false,
        "aliases": null
      }
    },
    "deprecated": null
  },
  "vmware.vmware.deploy_folder_template": {
    "short_description": "Deploy a VM from a template located in a folder",
    "description": "Create a VM from a template that is located in vCenter. The template must be found in a folder, as opposed to being in a content library. This module manages the deployed VM, not the template. The template will be unchanged. To further configure the VM, ensure it is deployed in the powered off state and then use other modules to configure it. The module basis idempotentency on if the deployed VM exists or not, not the storage or power settings applied at deployment time.",
    "options": {
      "template_name": {
        "description": "The name of the template to use when deploying. You must also supply O(template_folder) if you use this parameter. This parameter is not used if O(template_id) is supplied.",
        "type": "str",
        "required": false,
        "choices": null,
        "default": null,
        "aliases": null
      },
      "template_folder": {
        "description": "The path to the folder where the template with O(template_name) exists. This parameter is not used if O(template_id) is supplied. This can be an absolute (/datacenter/vm/my/folder) or relative (my/folder) path. This parameter is mutually exclusive with O(template_folder_id).",
        "type": "str",
        "required": false,
        "choices": null,
        "default": null,
        "aliases": null
      },
      "template_folder_id": {
        "description": "The ID of the folder where the template with O(template_name) exists. This parameter is not used if O(template_id) is supplied. This parameter is mutually exclusive with O(template_folder).",
        "type": "str",
        "required": false,
        "choices": null,
        "default": null,
        "aliases": null
      },
      "template_id": {
        "description": "The ID of the template to use when deploying. This parameter takes precedence over O(template_name) and O(template_folder)",
        "type": "str",
        "required": false,
        "choices": null,
        "default": null,
        "aliases": null
      },
      "esxi_host": {
        "description": "The name of the ESXi host onto which the virtual machine should be deployed. If O(esxi_host) and O(resource_pool) are both specified, O(resource_pool) must belong to O(esxi_host). If O(esxi_host) and O(cluster) are both specified, O(esxi_host) must be a member of O(cluster). Changing this option will not result in the VM being redeployed (it does not affect idempotency).",
        "type": "str",
        "required": false,
        "choices": null,
        "default": null,
        "aliases": [
          "host"
        ]
      },
      "power_on_after_deploy": {
        "description": "Whether or not the VM should be powered on once it has been deployed. This is only applied when the VM is deployed. If the VM already exists, the power state is not modified. Changing this option will not result in the VM being redeployed (it does not affect idempotency).",
        "type": "bool",
        "required": false,
        "choices": null,
        "default": false,
        "aliases": null
      }
    },
    "deprecated": null
  },
  "vmware.vmware.esxi_host": {
    "short_description": "Manage VMware ESXi host status in vCenter",
    "description": "Manage VMware ESXi host status in vCenter, including cluster or folder membership. The host must be in maintenance mode to remove it or update its placement. This module does not manage the connection status of hosts in vCenter. That functionality is in vmware.vmware.esxi_connection The host must be in maintenance mode if it is already registered with vCenter but should be moved to a new cluster or folder.",
    "options": {
      "cluster": {
        "description": "The name of the cluster to be managed. One of O(cluster) or O(folder) is required when O(state) is V(present). Since ESXi names are unique in a datacenter, this option is not used when O(state) is V(absent).",
        "type": "str",
        "required": false,
        "choices": null,
        "default": null,
        "aliases": [
          "cluster_name"
        ]
      },
      "datacenter": {
        "description": "The name of the datacenter.",
        "type": "str",
        "required": true,
        "choices": null,
        "default": null,
        "aliases": [
          "datacenter_name"
        ]
      },
      "folder": {
        "description": "Name of the folder under which host to add. One of O(cluster) or O(folder) is required when O(state) is V(present) Since ESXi names are unique in a datacenter, this option is not used when O(state) is V(absent).",
        "type": "str",
        "required": false,
        "choices": null,
        "default": null,
        "aliases": null
      },
      "folder_paths_are_absolute": {
        "description": "If true, any folder path parameters are treated as absolute paths. If false, modules will try to intelligently determine if the path is absolute or relative. This option is useful when your environment has a complex folder structure. By default, modules will try to intelligently determine if the path is absolute or relative. They may mistakenly prepend the datacenter name or other folder names, and this option can be used to avoid this.",
        "type": "bool",
        "required": false,
        "choices": null,
        "default": false,
        "aliases": null
      },
      "esxi_host_name": {
        "description": "ESXi hostname to manage.",
        "type": "str",
        "required": true,
        "choices": null,
        "default": null,
        "aliases": null
      },
      "esxi_username": {
        "description": "The username to use when authenticating to the ESXi host. Required when O(state) is V(present).",
        "type": "str",
        "required": false,
        "choices": null,
        "default": null,
        "aliases": null
      },
      "esxi_password": {
        "description": "The password to use when authenticating to the ESXi host. Required when O(state) is V(present).",
        "type": "str",
        "required": false,
        "choices": null,
        "default": null,
        "aliases": null
      },
      "esxi_port": {
        "description": "The port on which the ESXi host",
        "type": "str",
        "required": false,
        "choices": null,
        "default": null,
        "aliases": null
      }
    },
    "deprecated": null
  },
  "vmware.vmware.folder": {
    "short_description": "Manage VMware vSphere folders",
    "description": "Adds or removes VMware vSphere folders. This module does not manage folders inside of datastores.",
    "options": {
      "datacenter": {
        "description": "The name of the datacenter where the folder should be created. Only used if the O(relative_path) option is used.",
        "type": "str",
        "required": false,
        "choices": null,
        "default": null,
        "aliases": [
          "datacenter_name"
        ]
      },
      "folder_type": {
        "description": "The type of folder that should be created. The folder type controls what resources can be held in the folder, as well as the path where the folder is created. For example, a folder at path /DC-01/vm/my/folder has folder type",
        "type": "str",
        "required": false,
        "choices": null,
        "default": null,
        "aliases": null
      }
    },
    "deprecated": null
  },
  "vmware.vmware.folder_template_from_vm": {
    "short_description": "Create a template in a local VCenter folder from an existing VM",
    "description": "This module creates a template in a local VCenter folder from an existing VM. The folder must already exist. The VM must be powered off, and is otherwise unchanged. If the template already exists and the desired state is ",
    "options": {},
    "deprecated": null
  },
  "vmware.vmware.license_info": {
    "short_description": "Fetch VMware vCenter license keys",
    "description": "Fetch vCenter, ESXi server license keys.",
    "options": {},
    "deprecated": null
  },
  "vmware.vmware.local_content_library": {
    "short_description": "Manage a local content library.",
    "description": "Create, update, or destroy a local content library.",
    "options": {
      "name": {
        "description": "The name of the local content library to manage.",
        "type": "str",
        "required": true,
        "choices": null,
        "default": null,
        "aliases": [
          "library_name"
        ]
      },
      "description": {
        "description": "The description for the content library.",
        "type": "str",
        "required": false,
        "choices": null,
        "default": null,
        "aliases": [
          "library_description"
        ]
      }
    },
    "deprecated": null
  },
  "vmware.vmware.subscribed_content_library": {
    "short_description": "Manage a subscribed content library.",
    "description": "Create, update, or destroy a subscribed content library.",
    "options": {
      "name": {
        "description": "The name of the subscribed content library to manage.",
        "type": "str",
        "required": true,
        "choices": null,
        "default": null,
        "aliases": [
          "library_name"
        ]
      },
      "description": {
        "description": "The description for the content library.",
        "type": "str",
        "required": false,
        "choices": null,
        "default": null,
        "aliases": [
          "library_description"
        ]
      }
    },
    "deprecated": null
  },
  "vmware.vmware.tag_associations": {
    "short_description": "Manage the tags associated with a vSphere object.",
    "description": "This module allows you to attach and detach tags to a vSphere object. For better performance, use object IDs instead of names when possible.",
    "options": {
      "state": {
        "description": "Whether ensure the tags are present or absent on the object.",
        "type": "str",
        "required": false,
        "choices": [
          "present",
          "absent"
        ],
        "default": "present",
        "aliases": null
      },
      "remove_extra_tags": {
        "description": "Whether to remove tags that are not in the list of tags to manage. If O(state) is set to C(absent), all tags will be removed.",
        "type": "bool",
        "required": false,
        "choices": null,
        "default": false,
        "aliases": null
      },
      "tags": {
        "description": "A list of tags to manage.",
        "type": "list",
        "required": true,
        "choices": null,
        "default": null,
        "aliases": null
      },
      "object_moid": {
        "description": "The managed object ID (MOID) of the object to manage. One of O(object_moid) or O(object_name) is required.",
        "type": "str",
        "required": false,
        "choices": null,
        "default": null,
        "aliases": null
      },
      "object_name": {
        "description": "The name of the object to manage. One of O(object_moid) or O(object_name) is required.",
        "type": "str",
        "required": false,
        "choices": null,
        "default": null,
        "aliases": null
      },
      "object_type": {
        "description": "The type of the object to manage.",
        "type": "str",
        "required": true,
        "choices": [
          "VirtualMachine",
          "Datacenter",
          "ClusterComputeResource",
          "HostSystem",
          "DistributedVirtualSwitch",
          "DistributedVirtualPortgroup",
          "Datastore",
          "DatastoreCluster",
          "ResourcePool",
          "Folder"
        ],
        "default": null,
        "aliases": null
      },
      "validate_tags_before_attaching": {
        "description": "Whether to validate the tags before attaching them to the object. If true, additional API calls will be made to validate the tags exist and can be applied to the type of object specified. If a tag fails validation, an error will be raised. If false, the tags will be attached to the object without validation. This is faster, but may result in the module reporting changes every time. This is due to the module attempting to attach the tag, and vSphere simply ignoring the invalid request.",
        "type": "bool",
        "required": false,
        "choices": null,
        "default": false,
        "aliases": null
      }
    },
    "deprecated": null
  },
  "vmware.vmware.tag_categories": {
    "short_description": "Manage one or more VMware tag categories.",
    "description": "This module allows you to create, update, and delete VMware tag categories. For better performance, use object IDs instead of names when possible. For better performance, manage many tag categories per module call (as opposed to using a loop). See the examples for more details.",
    "options": {
      "state": {
        "description": "Whether ensure the tag categories are present or absent.",
        "type": "str",
        "required": false,
        "choices": [
          "present",
          "absent"
        ],
        "default": "present",
        "aliases": null
      },
      "tag_categories": {
        "description": "A list of tag categories to manage. Providing the ID instead of the name will reduce the number of API calls, and potentially speed up the module execution.",
        "type": "list",
        "required": true,
        "choices": null,
        "default": null,
        "aliases": null
      }
    },
    "deprecated": null
  },
  "vmware.vmware.tags": {
    "short_description": "Manage one or more VMware tags.",
    "description": "This module allows you to create, update, and delete VMware tags. For better performance, use object IDs instead of names when possible.",
    "options": {
      "state": {
        "description": "Whether ensure the tags are present or absent.",
        "type": "str",
        "required": false,
        "choices": [
          "present",
          "absent"
        ],
        "default": "present",
        "aliases": null
      },
      "tags": {
        "description": "A list of tags to manage.",
        "type": "list",
        "required": true,
        "choices": null,
        "default": null,
        "aliases": null
      }
    },
    "deprecated": null
  },
  "vmware.vmware.vcsa_backup_schedule": {
    "short_description": "Configure the vCenter Server Appliance backup schedule",
    "description": "Configure the vCenter Server Appliance backup schedule. Only one schedule per vCenter Server Appliance can exist. Before taking a backup, a backup server must be set up and configured such that the vCenter server has access to it. The protocols supported for backup are FTPS, HTTPS, SFTP, FTP, NFS, SMB and HTTP.",
    "options": {
      "name": {
        "description": "The name of the backup schedule. This must be unique, and is used as an identifier for the schedule. Your VCSA may only allow for one schedule. If you create this schedule via the web UI, its name is",
        "type": "str",
        "required": false,
        "choices": null,
        "default": null,
        "aliases": null
      }
    },
    "deprecated": null
  },
  "vmware.vmware.vcsa_backup_schedule_info": {
    "short_description": "Gather info about one or more VCSA backup schedules.",
    "description": "Gather info about vCenter server appliance backup schedules. If a name is provided, only the schedule with that name will be included in the output.",
    "options": {
      "name": {
        "description": "The name of the backup schedule for which to gather info. If no name is provided, all backup schedules are returned.",
        "type": "str",
        "required": false,
        "choices": null,
        "default": null,
        "aliases": null
      }
    },
    "deprecated": null
  },
  "vmware.vmware.vcsa_settings": {
    "short_description": "Configure vCenter Server Appliance settings",
    "description": "Configure vCenter Server Appliance settings.",
    "options": {
      "timezone": {
        "description": "Set time zone.",
        "type": "str",
        "required": false,
        "choices": null,
        "default": null,
        "aliases": null
      },
      "global_fips": {
        "description": "",
        "type": "str",
        "required": false,
        "choices": null,
        "default": null,
        "aliases": null
      }
    },
    "deprecated": null
  },
  "vmware.vmware.vm": {
    "short_description": "Create, update, or delete a virtual machine.",
    "description": "This module is used to create, update, or delete virtual machines. Although this module will attempt to validate your configuration, it is not feasible to validate all possible combinations of parameters. You may encounter errors when starting VMs with invalid configurations. Error messages may not always be very helpful. Checking the vCenter task logs or VM edit settings page may have additional messages.",
    "options": {
      "state": {
        "description": "Whether to ensure the VM is present or absent.",
        "type": "str",
        "required": false,
        "choices": [
          "present",
          "absent"
        ],
        "default": "present",
        "aliases": null
      },
      "name": {
        "description": "Name of the virtual machine to manage. Virtual machine names in vCenter are not necessarily unique, which may be problematic, see O(name_match). This is required when the VM does not exist, or if O(moid) or O(uuid) is not supplied.",
        "type": "str",
        "required": false,
        "choices": null,
        "default": null,
        "aliases": null
      },
      "name_match": {
        "description": "If multiple virtual machines matching the name, use the first or last found.",
        "type": "str",
        "required": false,
        "choices": [
          "first",
          "last"
        ],
        "default": "first",
        "aliases": null
      },
      "uuid": {
        "description": "UUID of the instance to manage if known, this is VMware",
        "type": "str",
        "required": false,
        "choices": null,
        "default": null,
        "aliases": null
      }
    },
    "deprecated": null
  },
  "vmware.vmware.vm_advanced_settings": {
    "short_description": "Manages the advanced settings for a VM",
    "description": "Manages the advanced settings for a VM. Changing advanced settings can cause instability for the VM. Be careful when removing or updating existing settings.",
    "options": {
      "datacenter": {
        "description": "The name of the datacenter to search for the VM. This is only used if O(folder) is also used.",
        "type": "str",
        "required": false,
        "choices": null,
        "default": null,
        "aliases": [
          "datacenter_name"
        ]
      },
      "state": {
        "description": "Set the state of the advanced settings on the VM. If present, the specified advanced settings are added to the VM if they are missing or the value is incorrect. If absent, the specified advanced settings are removed. If a setting is provided with an empty value, then the setting will be removed regardless of the current value on the VM.",
        "type": "str",
        "required": false,
        "choices": [
          "present",
          "absent"
        ],
        "default": "present",
        "aliases": null
      },
      "name": {
        "description": "Name of the virtual machine to work with. Virtual machine names in vCenter are not necessarily unique, which may be problematic, see O(name_match). This is required if O(moid) or O(uuid) is not supplied.",
        "type": "str",
        "required": false,
        "choices": null,
        "default": null,
        "aliases": null
      },
      "name_match": {
        "description": "If multiple virtual machines matching the name, use the first or last found.",
        "type": "str",
        "required": false,
        "choices": [
          "first",
          "last"
        ],
        "default": "first",
        "aliases": null
      },
      "uuid": {
        "description": "UUID of the instance to manage if known, this is VMware",
        "type": "str",
        "required": false,
        "choices": null,
        "default": null,
        "aliases": null
      }
    },
    "deprecated": null
  },
  "vmware.vmware.vm_apply_customization": {
    "short_description": "Applies a customization specification to a virtual machine.",
    "description": "This module is used to apply a customization specification to a virtual machine. It always applies the specification defined here, and always reports a change. Customization specifications are run once when a VM is powered on or rebooted. This module just applies the customization specification to the VM, making sure that it will be run during the next power cycle. Since customization is run asynchronously, you should check the VM logs to ensure that the customization was applied successfully. See the examples for ways to ensure the customization was applied successfully in a playbook. Once the VM is started, the pending customization is applied. Even if that fails, the customization is then cleared. Meaning, you need to re-apply the customization spec in order to try again. Simply rebooting the VM will not change anything. Customization leverages VMWare Tools to inject the customization specification into the VM. For a list of supported operating systems, see the Broadcom documentation http://partnerweb.vmware.com/programs/guestOS/guest-os-customization-matrix.pdf Custom script execution is disabled by default. To enable it, you can run as an administrator",
    "options": {},
    "deprecated": null
  },
  "vmware.vmware.vm_list_group_by_clusters_info": {
    "short_description": "",
    "description": "",
    "options": {},
    "deprecated": null
  },
  "vmware.vmware.vm_portgroup_info": {
    "short_description": "",
    "description": "",
    "options": {},
    "deprecated": null
  },
  "vmware.vmware.vm_powerstate": {
    "short_description": "Manages power states of virtual machines in vCenter",
    "description": "Manages power states of virtual machines in vCenter, e.g., Power on / Power off / Restart.",
    "options": {
      "datacenter": {
        "description": "The datacenter where the VM you",
        "type": "str",
        "required": false,
        "choices": null,
        "default": null,
        "aliases": null
      }
    },
    "deprecated": null
  },
  "vmware.vmware.vm_snapshot_revert": {
    "short_description": "Revert a virtual machine to a snapshot",
    "description": "This module can be used to revert a virtual machine to a snapshot. Since the virtual machine immediately begins to drift from the snapshot, this module will always attempt to revert the virtual machine. A change will always be reported. If the snapshot is not found, the module will fail.",
    "options": {
      "name": {
        "description": "Name of the virtual machine to work with. This is required parameter, if O(uuid) or O(moid) is not supplied.",
        "type": "str",
        "required": false,
        "choices": null,
        "default": null,
        "aliases": null
      },
      "name_match": {
        "description": "If multiple VMs with the same name exist, use the first or last found.",
        "type": "str",
        "required": false,
        "choices": null,
        "default": null,
        "aliases": null
      }
    },
    "deprecated": null
  }
}